{"Name":"apurva","Class":"Archer","Hitpoints":10,"MaxHitpoints":11,"Level":0,"Experience":0,"LevelPoints":1,"CurrentWeapon":{"DamageValue":1,"Name":"Bow","Quantity":1,"_Rarity":0},"CurrentHelmet":{"ArmorValue":0,"ArmorPiece":0,"Name":"Nothing","Quantity":0,"_Rarity":0},"CurrentBody":{"ArmorValue":1,"ArmorPiece":2,"Name":"Leather Body","Quantity":1,"_Rarity":0},"CurrentLegs":{"ArmorValue":1,"ArmorPiece":3,"Name":"Leather Legs","Quantity":1,"_Rarity":0},"CurrentBoots":{"ArmorValue":0,"ArmorPiece":0,"Name":"Nothing","Quantity":0,"_Rarity":0},"CurrentAmulet":{"Name":"Nothing","Quantity":0,"_Rarity":0},"CurrentRing":{"Name":"Nothing","Quantity":0,"_Rarity":0},"Abilities":[],"Inventory":[{"Name":"Potion","Quantity":1,"_Rarity":4}],"Ammunition":[{"DamageMultiplier":1,"Type":"Wooden","Name":"Wooden Arrow","Quantity":25,"_Rarity":0}],"Gold":0,"Consumeables":[{"Name":"Potion","Quantity":1,"_Rarity":4}],"Weapons":[],"Armors":[],"Jewleries":[],"Attributes":{"Vigor":1,"Endurance":1,"Strength":1,"Agility":1,"Cold Resistance":1,"Fire Resistance":1,"Lightning Resistance":1}}